[
  {
    "Title": "Tik Tik Vajate Dokyaat",
    "Artist": "Sayalie Pankaj, Sonu Nigam, Vaibhav Patole",
    "Duration": 172,
    "lyrics": "https://lrclib.net/api/search?q=Tik+Tik+Vajate+Dokyaat+Sayalie+Pankaj%2C+Sonu+Nigam%2C+Vaibhav+Patole",
    "status": "API Error",
    "lrc": false
  },
  {
    "Title": "Yad Lagla",
    "Artist": "Ajay Gogavale",
    "Duration": 314,
    "lyrics": "[00:44.38] याड लागलं गं याड लागलं गं\n[00:47.95] रंगलं तुझ्यातं याड लागलं गं\n[00:51.33] वास ह्यो उसात येई कस्तूरीचा\n[00:54.63] चाखलंया वारं ग्वाड लागलं गं\n[00:58.28] चांद भासतो दिसाच मावळाया लागलं\n[01:04.26] आस लागली मनात कालवाया लागलं\n[01:11.76] याड लागलं गं याड लागलं गं\n[01:15.17] रंगलं तुझ्यात याड लागलं गं\n[01:18.82] वास ह्यो उसात येई कस्तूरीचा\n[01:22.21] चाखलंया वारं ग्वाड लागलं गं\n[01:30.21] \n[01:59.91] सांगवंना बोलवंना\n[02:03.34] मन झुरतंया दुरून\n[02:06.86] पळतंया कळतंया\n[02:10.13] वळतंय मागं फिरून\n[02:13.82] सजलं गं धजलं गं\n[02:16.93] लाजं काजंला सारलं\n[02:20.41] येंधळं ह्ये गोंधळंलं\n[02:23.98] लाडंलाडं ग्येलं हरुन\n[02:27.32] भाळलं असं उरात पालवाया लागलं\n[02:33.73] हेऽऽ ओढ लागली मनात चाळवाया लागलं\n[02:40.64] याड लागलं गं याड लागलं गं\n[02:46.64] \n[04:08.38] सुलगंना उलगंना\n[04:12.55] जाळ आतल्या आतला\n[04:15.49] दुखनं ह्ये देखनं गं\n[04:18.75] एकलंच हाय साथीला\n[04:21.90] काजळीला उजळंलं\n[04:25.57] पाजळून ह्या वातीला\n[04:29.18] चांदनीला आवतान\n[04:32.49] धाडतुया रोज रातीला\n[04:36.00] झोप लागंना सपान जागवाया लागलं\n[04:41.93] पाखरू कसं आभाळ पांघराया लागलं\n[04:47.93] ",
    "status": "Synced",
    "lrc": true
  },
  {
    "Title": "Zindagi Zindagi",
    "Artist": "Sachin Pilgaonkar, Sumeet Raghvan",
    "Duration": 282,
    "lyrics": "[00:00.22] ज़िन्दगी ज़िन्दगी ज़िन्दगी, हां ज़िन्दगी\n[00:07.06] ज़िन्दगी ज़िन्दगी\n[00:10.26] दोस्तों की दुनियादारी में हसीन मेरी ज़िन्दगी\n[00:16.48] ऐसा क्या हुआ रे, ऐसा क्यों हुआ रे\n[00:19.88] Thought चा हा shot नको रे\n[00:22.77] थोडा कश मार ले, सावकाश मार रे\n[00:26.27] हलकी हलकी kick बसू दे\n[00:29.16] सारे गम छोड दे, एक दम ओढ ले\n[00:32.62] Smoke में ही hope है प्यारे\n[00:40.52] मै जिंदगी का साथ निभाता चला गया\n[00:43.65] हर फिक्र को धुंवे में उडाता चला गया\n[00:46.75] मै जिंदगी का साथ निभाता चला गया\n[00:49.98] हर फिक्र को धुंवे में उडा...\n[00:53.45] ज़िन्दगी ज़िन्दगी ज़िन्दगी, हा जिंदगी\n[00:59.79] ज़िन्दगी ज़िन्दगी\n[01:03.02] दोस्तों की दुनियादारी में हसीन मेरी जिंदगी\n[01:11.18] साला ही gang च वेगळी होती, कट्टा gang!\n[01:14.63] सगळ्यांशी आपली ओळख झाली\n[01:16.58] हा अश्क्या, हा कुणाचाच नव्हता, तरीही gang चा\n[01:21.56] हे उम्या आणि श्री\n[01:24.13] हे म्हणजे नवविवाहित दांपत्या सारखे\n[01:27.17] कुठेही गेले ना तरी एकत्र\n[01:29.58] आता राहिले Sorry आणि नित्या\n[01:32.15] यांची तर ना दिघ्याने मला एक special ओळख करून दिली\n[01:36.77] Sorry sorry म्हणत म्हणत, या जगी हा आला रे\n[01:39.76] (या जगी हा आला रे)\n[01:41.66] बात में है confusion, गडबड घोटाला रे\n[01:44.77] (गडबड घोटाला रे)\n[01:46.42] दस का बीस करने में, शातिर ये साला रे\n[01:49.50] (शातिर ये साला रे)\n[01:51.14] झोल-झोल करुनी तरी ठण ठण गोपाळा रे\n[01:54.26] (ठण ठण गोपाळा रे)\n[01:57.34] अरे यारी में sorry आये तो गलत है\n[02:00.48] पर अपने Sorry की तो बात अलग है\n[02:06.83] ये झोलर कमीना, सोचता कभी ना\n[02:10.32] यारी में ही झोल छुपा है (याच्या आईला ह्याच्या)\n[02:15.25] झोल में ही यारी छुपी है\n[02:21.31] मै ज़िन्दगी का साथ निभाता चला गया\n[02:24.38] हर फिक्र को धुंवे में उडाता चला गया\n[02:27.67] मै ज़िन्दगी का साथ निभाता चला गया\n[02:30.73] हर फिक्र को धुंवे में उडा... ज़िन्दगी\n[02:36.94] दिघ्या बरोबर मी पहिली cigarette प्यायलो\n[02:39.82] दिघ्या, आपला पहिला friend\n[02:42.52] आणि त्याच बरोबर मला कळलेल दिघ्याचे पहिले प्रेम\n[02:46.70] च्याआईला, लफडी करताना पुढचा मागचा विचार न करणारा हा माणूस\n[02:51.22] प्रेमाच्या लफड्यात मात्र\n[02:56.93] हो, जेव्हा पाहिलं हिला, ये दिल हिल्ला-हिल्ला\n[03:01.07] सारा जिल्हा हिल्ला, हुआ रे जलजला\n[03:11.26] हो, जेव्हा पाहिलं हिला, ये दिल हिल्ला-हिल्ला\n[03:15.43] सारा जिल्हा हिल्ला, हुआ रे जलजला\n[03:19.02] घराच्या सामोरी नजरेची शाळा ही, रोज रोज भरवायची हाय\n[03:25.39] लैला नि मजनूची sad वाली love story आपल्याला बदलायची हाय-हाय-हाय\n[03:31.59] ही सुरेखा, आपल्याला पटलेली हाय (हाय)\n[03:36.41] अरे खिडकीमधून कशी लाजून हसलेली हाय (हाय)\n[03:41.13] अरे हसली-हसली दिघ्या फूल टू फसलेली हाय (हाय)\n[03:46.37] हसलेली हाय, फसलेली हाय, दिघ्याला पटलेली हाय\n[03:53.26] कधी ह्यांचे होऊन गेले हो कळलेच नाही\n[03:55.49] एक वेगळीच दुनिया, एक वेगळीच दुनियादारी\n[04:00.53] मै ज़िन्दगी का साथ निभाता चला गया\n[04:03.48] हर फिक्र को धुंवे में उडाता चला गया\n[04:06.39] मै ज़िन्दगी का साथ निभाता चला गया\n[04:08.76] हर फिक्र को धुंवे में उडा...\n[04:11.94] ज़िन्दगी ज़िन्दगी ज़िन्दगी, मेरी ज़िन्दगी\n[04:17.33] ज़िन्दगी जिंदगी\n[04:20.14] दोस्तों की दुनियादारी में हसीन मेरी ज़िन्दगी\n[04:24.28] ज़िन्दगी ज़िन्दगी, हां ज़िन्दगी\n[04:28.45] ज़िन्दगी ज़िन्दगी\n[04:31.29] ज़िन्दगी, हां ज़िन्दगी...\n[04:38.98] ",
    "status": "Synced",
    "lrc": true
  },
  {
    "Title": "Zingaat",
    "Artist": "Ajay-Atul",
    "Duration": 232,
    "lyrics": "https://lrclib.net/api/search?q=Zingaat+Ajay-Atul",
    "status": "API Error",
    "lrc": false
  }
]